avmath/__init__.py
avmath/algebra.py
avmath/analysis.py
avmath-3.1.1.dist-info/LICENSE.txt
avmath-3.1.1.dist-info/METADATA
avmath-3.1.1.dist-info/WHEEL
avmath-3.1.1.dist-info/top_level.txt
avmath-3.1.1.dist-info/RECORD
