Metadata-Version: 2.1
Name: avmath
Version: 3.1.1
Summary: Avmath math module
Home-page: https://github.com/ballandt/avmath
Author: Camillo Ballandt
Author-email: ballandt@protonmail.com
License: MIT
Project-URL: Documentation, https://github.com/ballandt/avmath/wiki/Documentation
Platform: UNKNOWN
Classifier: Programming Language :: Python :: 3
Classifier: License :: OSI Approved :: MIT License
Classifier: Operating System :: OS Independent
Requires-Python: >=3.10
License-File: LICENSE.txt
